sdriq2complex/__init__.py
sdriq2complex/sdriq2complex.py
sdriq2complex-0.0.1.data/scripts/sdriq2complex
sdriq2complex-0.0.1.dist-info/LICENSE
sdriq2complex-0.0.1.dist-info/METADATA
sdriq2complex-0.0.1.dist-info/WHEEL
sdriq2complex-0.0.1.dist-info/top_level.txt
sdriq2complex-0.0.1.dist-info/RECORD
