Metadata-Version: 2.1
Name: sdriq2complex
Version: 0.0.1
Summary: SDRangel *.srdiq data conversion tool
Home-page: https://github.com/mehanik/sdriq2complex
Author: Eugene Mikhantiev
Author-email: mikhantiev@gmail.com
License: UNKNOWN
Platform: UNKNOWN
Classifier: Programming Language :: Python :: 3
Classifier: License :: OSI Approved :: MIT License
Classifier: Operating System :: OS Independent
Requires-Python: >=3.6
Requires-Dist: numpy
